{
  "id": "0x07aa8192df23cc98353c511d0c679ef3b9ddb1ea",
  "timestamp": 1734283883000,
  "author": {
    "username": "paul-prudence",
    "displayname": "Paul Prudence",
    "fid": 307224,
    "avatar": "https://i.imgur.com/1wOpavr.jpg",
    "description": "Artist/Writer /the-library /geoblocks ✷ https://linktr.ee/paulprudence ✷ Live: ISO/IEC 10646 ⟶  https://verse.works/series/iso-iec-10646-by-paul-prudence"
  },
  "text": "Bethany Collins\nSouthern Review, 1985",
  "images": [
    "https://imagedelivery.net/BXluQx4ige9GuW0Ia56BHw/c88bb11e-a6a7-4cad-340e-df2bbd232300/original"
  ]
}