{
  "id": "0x1eab447f08595a5bf719165cd0030747d50be109",
  "timestamp": 1717190212000,
  "author": {
    "username": "pixelsymphony",
    "displayname": "Pixel Symphony",
    "fid": 232704,
    "avatar": "https://i.imgur.com/9rfO3oM.jpg",
    "description": "Generative Artist with a Master’s in History of Modern Art & Curatorial Studies. Building\nAtelierArt.io. HUG 100 Artists to Watch.\n\n\nWebsite: pixelsymphony.art"
  },
  "text": "Wlademir Dias Pino, from solida (1957) with the second phase of poem on facing page.\n\nsolida = solid\nsolidão = solitude\nso = only\nlida = works (third person singular)\nsol = sun\nsaido = gone out\nda lido do dia = from the day's labor",
  "images": [
    "https://imagedelivery.net/BXluQx4ige9GuW0Ia56BHw/bd7aa1ee-f1d2-4dfa-72ff-ebdff8f28900/original"
  ]
}