{
  "id": "0x212aa9c83f5c1aa30bfc32d3d612be3d2d5fd0ce",
  "timestamp": 1756972530000,
  "author": {
    "username": "pixelsymphony",
    "displayname": "Pixel Symphony",
    "fid": 232704,
    "avatar": "https://imagedelivery.net/BXluQx4ige9GuW0Ia56BHw/f3b24f61-2f5c-4b34-ad85-44203f7e3f00/rectcrop3",
    "description": "Generative Artist with a Master’s in History of Modern Art & Curatorial Studies. Building\nAtelierArt.io. HUG 100 Artists to Watch.\n\n\nWebsite: pixelsymphony.art"
  },
  "text": "",
  "images": [
    "https://imagedelivery.net/BXluQx4ige9GuW0Ia56BHw/2329b8b5-4223-4e54-ce13-bf6b5797e300/original"
  ]
}