{
  "id": "0x2acc0656996c1f986981b1f01ddcde0ab5090b9e",
  "timestamp": 1733757859000,
  "author": {
    "username": "entter",
    "displayname": "entter",
    "fid": 335383,
    "avatar": "https://imagedelivery.net/BXluQx4ige9GuW0Ia56BHw/b09c8604-92f7-4e5f-43ae-bf0b89ec0800/original",
    "description": "THE POPE OF PIXEL https://linktr.ee/vjentter"
  },
  "text": "'i did not have to give up so much of myself to fit somewhere i did not even want to be' \n\nThe text is silhouetting the deer\n\nby @tinyrainboot",
  "images": [
    "https://imagedelivery.net/BXluQx4ige9GuW0Ia56BHw/df7bbd10-bdab-4210-70c9-7cfaea764f00/original"
  ]
}