{
  "id": "0x46bfe17dd5968b3295c96b24ffef80ef85a17940",
  "timestamp": 1711993345000,
  "author": {
    "username": "kflemmer",
    "displayname": "KF | Wild MissingNos.",
    "fid": 415689,
    "avatar": "https://i.imgur.com/w55GDl9.jpg",
    "description": "Kyle Flemmer | writer, publisher, digital media artist | http://objkt.com/profile/kflemmer"
  },
  "text": "It's Poetry Month all across North America! To celebrate, here's my fav visual sonnet 🥳\n\nMoonshot Sonnet (1964) by Mary Ellen Solt",
  "images": [
    "https://imagedelivery.net/BXluQx4ige9GuW0Ia56BHw/d38db65d-2343-4ec7-cfa6-ef3af5591000/original"
  ]
}