{
  "id": "0x49f675d9cf66a524285d1c5d40d0d973060b2eb3",
  "timestamp": 1752217456000,
  "author": {
    "username": "paul-prudence",
    "displayname": "Paul Prudence",
    "fid": 307224,
    "avatar": "https://i.imgur.com/1wOpavr.jpg",
    "description": "Artist/Writer /the-library /geoblocks ✷ https://linktr.ee/paulprudence ✷ Live: ISO/IEC 10646 ⟶  https://verse.works/series/iso-iec-10646-by-paul-prudence"
  },
  "text": "A Logical Conjunction",
  "images": [
    "https://imagedelivery.net/BXluQx4ige9GuW0Ia56BHw/cd3a4434-8730-4db6-8500-fd29235d4700/original"
  ]
}