{
  "id": "0x6200564076b9c22175f1a298b85ccc86d6e56649",
  "timestamp": 1724073414000,
  "author": {
    "username": "entter",
    "displayname": "entter",
    "fid": 335383,
    "avatar": "https://i.imgur.com/YYCIPvZ.png",
    "description": "Digital artist, curator, former VJ. I make art with old computers and video games since 2005. https://linktr.ee/vjentter"
  },
  "text": "FREE*\n\n*You pay mint fees and gas only\n\nby @obxium 2023\n\nhttps://superrare.com/artwork/eth/0xb932a70a57673d89f4acffbe830e8ed7f75fb9e0/46831",
  "images": [
    "https://imagedelivery.net/BXluQx4ige9GuW0Ia56BHw/49f86b5e-56ee-4b74-b44e-4529c64cfa00/original"
  ]
}