{
  "id": "0x8763e46938cc634c5374e531fc71749a3ca28082",
  "timestamp": 1719239571000,
  "author": {
    "username": "aether",
    "displayname": "æther",
    "fid": 14199,
    "avatar": "https://i.imgur.com/9hjl7Lg.png",
    "description": "artist, poet, eNFanT terrible ︳ cofounder atelierart.io ︳visualpoetry.io "
  },
  "text": "'Untitled' (ca early 1970's) \nby J.B. Murray\n\nink + marker on paper",
  "images": [
    "https://imagedelivery.net/BXluQx4ige9GuW0Ia56BHw/b27bf9d4-240c-4afc-4806-ff187960df00/original"
  ],
  "recast_by": {
    "username": "wonow",
    "displayname": "w.o.n.o.w •|°",
    "fid": 376665,
    "avatar": "https://i.imgur.com/FILSH46.jpg",
    "description": "\"grossiga mpfa habla horem\",\nKarawane, Von Hugo Ball, 1916 \n\nlinktr.ee/wonow\n\n"
  },
  "recast_hash": "0x3a56052a0cc6c43bbd381c7e319d1df54daeb000"
}