{
  "id": "0x897244fab747199d0e14b3c631b9c09cedb28a01",
  "timestamp": 1732210601000,
  "author": {
    "username": "nemocake",
    "displayname": "conrad",
    "fid": 248872,
    "avatar": "https://i.imgur.com/OiwNUs6.gif",
    "description": "Collection Lead for @lerandomart┊art collector/researcher & music junky\n\nhttps://www.lerandom.art"
  },
  "text": "Gilles Furtwängler, Dignité, 2023.",
  "images": [
    "https://imagedelivery.net/BXluQx4ige9GuW0Ia56BHw/ff9787f9-3674-4907-68af-e674b66d8c00/original"
  ]
}