{
  "id": "0x9547627ca8a78e419e01af1f807621b73df81f7c",
  "timestamp": 1732050282000,
  "author": {
    "username": "paul-prudence",
    "displayname": "Paul Prudence",
    "fid": 307224,
    "avatar": "https://i.imgur.com/1wOpavr.jpg",
    "description": "Artist/Writer /the-library /geoblocks ✷ https://linktr.ee/paulprudence ✷ Live: ISO/IEC 10646 ⟶  https://verse.works/exhibitions/iso-iec"
  },
  "text": "Matt Mullican\nUntitled from 88 Maps, 2010",
  "images": [
    "https://imagedelivery.net/BXluQx4ige9GuW0Ia56BHw/8ca38a98-4253-4442-e3c1-580ac66fc800/original"
  ]
}