{
  "id": "0x9d0d6ca36e2cd3e6c9b5c29077bcac9d6f08a562",
  "timestamp": 1755428849000,
  "author": {
    "username": "galeriemet",
    "displayname": "Galerie Met",
    "fid": 330050,
    "avatar": "https://i.imgur.com/VT3AzAe.jpg",
    "description": "Art gallery in Berlin with a focus on contemporary art, and digital art in Metaverse. | Mariannenstrasse 33, 10999 Berlin.\n\nhttps://galeriemet.com"
  },
  "text": "Sunday reading:\n\nI. THE SERVER ROOM\n\nApril is the cruellest month, caching data from the sleep-deprived land, stirring dead pixels with springtime protocols, mixing latency and memory leaks. Winter kept us buffered, covering interfaces in silent frost, feeding a little life on compressed streams. Summer surprised us, coming over the fiber line with a burst of heat and notifications. We paused in the chatbox, and went on in sunlight, into the digital courtyard, and clicked refresh. He said, “Marie, Marie, hold still. You are glitching.” And I was reassembled on the screen.\n\nPart 1/5 from\nRJ \nwaste.land, 2025\nText and audio, in collaboration with AI\nafter T.S.Eliot ‘The Wasteland’ (1922)\nMP4\n1280 x 780 pixels\non @objktcom",
  "images": [
    "https://imagedelivery.net/BXluQx4ige9GuW0Ia56BHw/ac8e5288-e23e-487b-7855-0beb7735f200/original"
  ]
}