{
  "id": "0xa78b8025e39aaa244225df669c4157f33cb7bbd2",
  "timestamp": 1760093265000,
  "author": {
    "username": "entter",
    "displayname": "entter",
    "fid": 335383,
    "avatar": "https://imagedelivery.net/BXluQx4ige9GuW0Ia56BHw/524569bd-38ce-4e16-9cb8-02cc46a58400/original",
    "description": "Artist\nhttp://linktr.ee/vjentter"
  },
  "text": "Shanzhai Lyric is a collaborative art and research project by Ming Lin and Alexandra Tatarsky that archives and transforms awkward, mistranslated slogans from Chinese bootleg clothing into an ongoing, multi-platform poem.",
  "images": [
    "https://imagedelivery.net/BXluQx4ige9GuW0Ia56BHw/3a3e51c6-98c0-40f5-85f3-15895e265800/original"
  ]
}