{
  "id": "0xc96935440e6e79eb8254b2d54fbe30e04b86a980",
  "timestamp": 1714995300000,
  "author": {
    "username": "pixellare",
    "displayname": "p.i.x.e.l.l.a.r.e.",
    "fid": 447323,
    "avatar": "https://i.imgur.com/lr0jJtf.png",
    "description": "designer who works in 2D > 4D ... \np.i.x.e.l.l.a.r.e. is a digital project involving blahblah ... https://rc.xyz/pixellare"
  },
  "text": "v.i.s.u.a.l.w.o.r.d.s.",
  "images": [
    "https://imagedelivery.net/BXluQx4ige9GuW0Ia56BHw/6f601180-d28d-40cb-affc-35b5a81c5e00/original"
  ]
}