{
  "id": "0xdbb8e81f9029e5c933dd9cfd8d7ed76ecd794b7d",
  "timestamp": 1726675813000,
  "author": {
    "username": "alidasun",
    "displayname": "Alida Sun",
    "fid": 473073,
    "avatar": "https://i.imgur.com/Tv4dtVo.jpg",
    "description": "Generative artist ; @artblocks Curated ; over 1,900 days & nights of hand coded generative art ☀️ "
  },
  "text": "Synthesthesia noise screenshot",
  "images": [
    "https://imagedelivery.net/BXluQx4ige9GuW0Ia56BHw/68d6bb74-359a-43dc-9960-f403c175a100/original"
  ],
  "recast_by": {
    "username": "samanthaeharvey",
    "displayname": "SEH",
    "fid": 456814,
    "avatar": "https://i.imgur.com/z2P47DR.jpg",
    "description": "Visual Artist \n• Sensory Art \n• Alternate Sensory-Friendly Experiences \n• Web3, Technology, Poetry\n• Founder SULCI WORLD\n• https://lit.link/samanthaharvey"
  },
  "recast_hash": "0x2acb4422b6999ab9314ee3c594cfb8799f016b66"
}