{
  "id": "0xebb0d9df4b6a62dfb7d991d7356a36ddafbee965",
  "timestamp": 1726763421000,
  "author": {
    "username": "entter",
    "displayname": "entter",
    "fid": 335383,
    "avatar": "https://i.imgur.com/YYCIPvZ.png",
    "description": "Digital artist, curator, former VJ. I make art with old computers and video games since 2005. https://linktr.ee/vjentter"
  },
  "text": "Gazing through the glass\nGabriel Alcala, 2024",
  "images": [
    "https://imagedelivery.net/BXluQx4ige9GuW0Ia56BHw/55c4839d-5f6d-4d72-4142-1628262e4c00/original"
  ]
}